isa_malagasy/__init__.py
isa_malagasy/isamalagasy.py
isa_malagasy-1.1.dist-info/LICENSE
isa_malagasy-1.1.dist-info/METADATA
isa_malagasy-1.1.dist-info/WHEEL
isa_malagasy-1.1.dist-info/top_level.txt
isa_malagasy-1.1.dist-info/RECORD
