Metadata-Version: 2.1
Name: isa-malagasy
Version: 1.1
Summary: Une bibliothèque pour convertir les nombres en lettres en malagasy.
Home-page: https://github.com/Daylamiy06
Author: Day Lamiy
Author-email: hatsudai1@gmail.com
License: Propriétaire
Classifier: Programming Language :: Python :: 3
Classifier: License :: Other/Proprietary License
Classifier: Operating System :: OS Independent
Requires-Python: >=3.6
License-File: LICENSE
